LICENSE
README.md
pyproject.toml
modern_i18n/__init__.py
modern_i18n/i18n.py
modern_i18n.egg-info/PKG-INFO
modern_i18n.egg-info/SOURCES.txt
modern_i18n.egg-info/dependency_links.txt
modern_i18n.egg-info/top_level.txt