Metadata-Version: 2.4
Name: modern-i18n
Version: 1.0.0
Summary: Modern-i18n is a modern library for internationalization (i18n) in Python projects.
Maintainer-email: Isaev Abbas <abbas.isaev@gmail.com>
Project-URL: Homepage, https://github.com/AbbasIsaev/modern-i18n
Project-URL: Repository, https://github.com/AbbasIsaev/modern-i18n.git
Keywords: modern-i18n,i18n
Classifier: Programming Language :: Python :: 3
Classifier: License :: OSI Approved :: MIT License
Classifier: Operating System :: OS Independent
Requires-Python: >=3.5
License-File: LICENSE
Dynamic: license-file
